fairmlhealth/__fairness_metrics.py
fairmlhealth/__init__.py
fairmlhealth/__kdd2020_tutorial_helpers.py
fairmlhealth/__mimic_data.py
fairmlhealth/__preprocessing.py
fairmlhealth/__utils.py
fairmlhealth/__validation.py
fairmlhealth/measure.py
fairmlhealth/performance_metrics.py
fairmlhealth/report.py
fairmlhealth/stat_utils.py
test/__init__.py
test/__utils.py
test/notebook_tester.py
test/test___utils.py
test/test_docs.py
test/test_example_toolusage_binary.py
test/test_example_toolusage_regression.py
test/test_fairnessmetrics.py
test/test_measure.py
test/test_performancemetrics.py
test/test_report.py
test/test_stat_utils.py
test/test_tutorial_evaluatingbinaryclassification.py
test/test_tutorial_evaluatingregression.py
fairmlhealth-1.0.2.dist-info/LICENSE.txt
fairmlhealth-1.0.2.dist-info/METADATA
fairmlhealth-1.0.2.dist-info/WHEEL
fairmlhealth-1.0.2.dist-info/top_level.txt
fairmlhealth-1.0.2.dist-info/RECORD
