Metadata-Version: 2.1
Name: fairmlhealth
Version: 1.0.2
Summary: Health-centered variation analysis
Home-page: https://github.com/KenSciResearch/fairMLHealth
Author: Christine Allen
Author-email: ca.magallen@gmail.com
License: UNKNOWN
Project-URL: KenSci, https://www.kensci.com
Project-URL: GitHub Pages, https://kensciresearch.github.io/fairMLHealth
Keywords: healthcare,machine learning,fairness,fair ML,responsible AI
Platform: UNKNOWN
Classifier: Development Status :: 4 - Beta
Classifier: License :: OSI Approved :: MIT License
Classifier: Programming Language :: Python :: 3
Requires-Python: <4,>=3.6
License-File: LICENSE.txt
Requires-Dist: aif360 (<=0.4.0,>=0.3.0)
Requires-Dist: ipython
Requires-Dist: jupyter
Requires-Dist: numpy (>=1.16)
Requires-Dist: pandas (>=1.0.3)
Requires-Dist: requests
Requires-Dist: scipy (<1.6.0,>=1.4.1)
Requires-Dist: scikit-learn (>=0.21)
Provides-Extra: dev
Requires-Dist: pytest (==5.4.2) ; extra == 'dev'
Requires-Dist: ipyparallel ; extra == 'dev'
Requires-Dist: nbformat ; extra == 'dev'
Requires-Dist: nbconvert ; extra == 'dev'
Requires-Dist: regex ; extra == 'dev'
Requires-Dist: matplotlib ; extra == 'dev'
Requires-Dist: seaborn ; extra == 'dev'
Requires-Dist: xgboost ; extra == 'dev'
Requires-Dist: pypiwin32 ; (platform_system == "Windows") and extra == 'dev'
Requires-Dist: pywin32 ; (platform_system == "Windows") and extra == 'dev'
Provides-Extra: license_files
Requires-Dist: LICENSE.txt ; extra == 'license_files'
Provides-Extra: tests
Requires-Dist: pytest (==5.4.2) ; extra == 'tests'
Requires-Dist: ipyparallel ; extra == 'tests'
Requires-Dist: nbformat ; extra == 'tests'
Requires-Dist: nbconvert ; extra == 'tests'
Requires-Dist: regex ; extra == 'tests'
Requires-Dist: pypiwin32 ; (platform_system == "Windows") and extra == 'tests'
Requires-Dist: pywin32 ; (platform_system == "Windows") and extra == 'tests'
Provides-Extra: tutorials
Requires-Dist: matplotlib ; extra == 'tutorials'
Requires-Dist: seaborn ; extra == 'tutorials'
Requires-Dist: xgboost ; extra == 'tutorials'
